ft6x36.py
micropython_ft6x36-0.1.0.dist-info/METADATA
micropython_ft6x36-0.1.0.dist-info/WHEEL
micropython_ft6x36-0.1.0.dist-info/top_level.txt
micropython_ft6x36-0.1.0.dist-info/RECORD
